{"chunk_definitions":[{"row":28,"row_count":1,"visible":true,"expansion_state":0,"options":{},"document_id":"C5CDB471","chunk_id":"cot8dw9czyq1q","chunk_label":"unnamed-chunk-2"},{"row":36,"row_count":1,"visible":true,"expansion_state":0,"options":{},"document_id":"C5CDB471","chunk_id":"coupe42pxsce4","chunk_label":"unnamed-chunk-3"},{"row":45,"row_count":1,"visible":true,"expansion_state":0,"options":{},"document_id":"C5CDB471","chunk_id":"cvlf7aiesmty9","chunk_label":"unnamed-chunk-4"}],"doc_write_time":1719160094,"chunk_rendered_width":400}